tests/__init__.py
tests/run_all_tests.py
tests/test_known_hosts.py
tests/test_known_merge.py
tests/test_scan.py
tests/test_scan_mock.py
ubuntuwebscanner-1.0.19.dist-info/licenses/LICENSE
ubuntuwebserver/__init__.py
ubuntuwebserver/app.py
ubuntuwebserver/config.py
ubuntuwebserver/deep_scan.py
ubuntuwebserver/insert_known_host.py
ubuntuwebserver/scanScript.py
ubuntuwebserver/templates/scan_results.html
ubuntuwebscanner-1.0.19.dist-info/METADATA
ubuntuwebscanner-1.0.19.dist-info/WHEEL
ubuntuwebscanner-1.0.19.dist-info/entry_points.txt
ubuntuwebscanner-1.0.19.dist-info/top_level.txt
ubuntuwebscanner-1.0.19.dist-info/RECORD
