Metadata-Version: 2.4
Name: ubuntuwebscanner
Version: 1.0.19
Summary: A lightweight Flask-based dashboard for scanning and monitoring LAN devices
Home-page: https://github.com/tjohnsonII/UbuntuWebServer
Author: Timothy Johnson II
Author-email: tiomthyallenjohnsonii@gmail.com
License: MIT
Classifier: Development Status :: 4 - Beta
Classifier: Intended Audience :: System Administrators
Classifier: Topic :: System :: Networking :: Monitoring
Classifier: Operating System :: POSIX :: Linux
Classifier: Programming Language :: Python :: 3
Classifier: Programming Language :: Python :: 3.10
Classifier: Programming Language :: Python :: 3.11
Classifier: Programming Language :: Python :: 3.12
Classifier: Framework :: Flask
Requires-Python: >=3.10
License-File: LICENSE
Requires-Dist: flask
Requires-Dist: manuf
Requires-Dist: mac-vendor-lookup
Requires-Dist: aiofiles
Requires-Dist: python-dotenv
Requires-Dist: psutil
Dynamic: license-file
